
{"messageId":"4053103e-d1a1-473b-a3c8-70a9747e2257","messageType":"performance-metrics","timestamp":1520487854126,"payload":{"ClientId":"public","BusinessServiceId":"public","entrytime":"2018-03-08 13:44:12","component":"BPS","scId":"6e79ff1f-158c-45dd-8a5c-61512b09e020","tenant":"TENANT1","user":"admin","serviceId":"5","txId":"3031","businessKey":"CC000000022354","trackedExecutionId":"WEB-RESUME","endToEnd":2095,"sumInternal":166,"sumExternal":"1929xyz","sumCxCall":0,"sumEaCall":1768,"sumDaCall":2,"sumPersistence":161,"EventPayload":{"details":[{"executionTime":"0","additionalData":"Alpha Missing Info","trackedExecutionId":"DA-CALL-NODE","timestamp":"2018-03-08 13:44:12"},{"executionTime":"0","additionalData":"Alpha Credit Card","trackedExecutionId":"DA-CALL-NODE","timestamp":"2018-03-08 13:44:12"},{"executionTime":"1764","additionalData":"Alpha Bureau Access Strategy","trackedExecutionId":"ENRICHMENT","timestamp":"2018-03-08 13:44:13"},{"executionTime":"1768","additionalData":"AlphaBureau Enrichment Call","trackedExecutionId":"ENRICHMENT-CALL-NODE","timestamp":"2018-03-08 13:44:13"},{"executionTime":"1","additionalData":"Alpha Credit Card","trackedExecutionId":"DA-CALL-NODE","timestamp":"2018-03-08 13:44:13"},{"executionTime":"1","additionalData":"Alpha Credit Card","trackedExecutionId":"DA-CALL-NODE","timestamp":"2018-03-08 13:44:13"},{"executionTime":"161","additionalData":"Persist","trackedExecutionId":"DB-PERSIST-NODE","timestamp":"2018-03-08 13:44:14"},{"executionTime":"2088","additionalData":"NEW:New App","trackedExecutionId":"WEB-EXEC-FILTER","timestamp":"2018-03-08 13:44:14"},{"executionTime":"2095","additionalData":"","trackedExecutionId":"WEB-RESUME","timestamp":"2018-03-08 13:44:14"}]}}}
{"messageId":"d58c29e7-cc4b-4dce-af6b-259124883098","messageType":"performance-metrics","timestamp":1520487854130,"payload":{"ClientId":"public","BusinessServiceId":"public","entrytime":"2018-03-08 13:44:11","component":"BPS","scId":"bd511696-8739-40ae-ab2f-6ea610d172cd","tenant":"TENANT1","user":"admin","serviceId":"5","txId":"3032","businessKey":"CC000000022333","trackedExecutionId":"WEB-RESUME","endToEnd":2250,"sumInternal":221,"sumExternal":2029,"sumCxCall":0,"sumEaCall":1918,"sumDaCall":4,"sumPersistence":111,"EventPayload":{"details":[{"executionTime":"0","additionalData":"Alpha Missing Info","trackedExecutionId":"DA-CALL-NODE","timestamp":"2018-03-08 13:44:11"},{"executionTime":"1","additionalData":"Alpha Credit Card","trackedExecutionId":"DA-CALL-NODE","timestamp":"2018-03-08 13:44:11"},{"executionTime":"1915","additionalData":"Alpha Bureau Access Strategy","trackedExecutionId":"ENRICHMENT","timestamp":"2018-03-08 13:44:13"},{"executionTime":"1918","additionalData":"AlphaBureau Enrichment Call","trackedExecutionId":"ENRICHMENT-CALL-NODE","timestamp":"2018-03-08 13:44:13"},{"executionTime":"3","additionalData":"Alpha Credit Card","trackedExecutionId":"DA-CALL-NODE","timestamp":"2018-03-08 13:44:13"},{"executionTime":"0","additionalData":"Alpha Credit Card","trackedExecutionId":"DA-CALL-NODE","timestamp":"2018-03-08 13:44:13"},{"executionTime":"111","additionalData":"Persist","trackedExecutionId":"DB-PERSIST-NODE","timestamp":"2018-03-08 13:44:13"},{"executionTime":"2227","additionalData":"NEW:New App","trackedExecutionId":"WEB-EXEC-FILTER","timestamp":"2018-03-08 13:44:14"},{"executionTime":"2250","additionalData":"","trackedExecutionId":"WEB-RESUME","timestamp":"2018-03-08 13:44:14"}]}}}
